{
  "status": "pass",
  "taskId": "S007C",
  "checkedAt": "2026-06-07T20:14:56",
  "runId": "ns504-df37c4e246844711812ab3a0cac40332-c",
  "aiJobId": "1bafc44f-241e-472d-aefd-8d9aeb6d2e65",
  "confirm": {
    "questionItemId": "32d19412-1ad1-4c6a-8713-fec049321ac2",
    "knowledgeMappingId": "93879665-7e46-456a-a13e-7d3b3f9ce621",
    "status": "confirmed"
  },
  "undo": {
    "removedQuestionItemId": "32d19412-1ad1-4c6a-8713-fec049321ac2",
    "removedKnowledgeMappingCount": 1,
    "status": "undone"
  },
  "questionCount": {
    "before": 6949,
    "afterConfirm": 6950,
    "afterUndo": 6949
  },
  "conclusion": "teacher confirmation writes QuestionItem and KnowledgeMapping only after review, and undo restores previous state"
}
