{
  "status": "pass",
  "taskId": "S006B",
  "checkedAt": "2026-06-23T23:50:26",
  "requestedApiPort": 7290,
  "resolvedApiPort": 7290,
  "portFallbackApplied": false,
  "sourceDocumentId": "86791a05-6381-4038-9bad-91c3c2811e01",
  "actions": {
    "merge": {
      "touched": 3,
      "createdCandidates": 0
    },
    "split": {
      "touched": 1,
      "createdCandidates": 2
    },
    "associate": {
      "touched": 1
    },
    "save_question": {
      "touched": 1,
      "createdQuestionId": "9a8a30b8-df6e-4780-b3d2-8a7c7ffeb7cc"
    }
  },
  "conclusion": "manual takeover workbench API supports merge split associate and save question chain"
}
