{
  "status": "pass",
  "taskId": "S010B",
  "checkedAt": "2026-06-23T13:31:25.684412+00:00",
  "paperBasketId": "51045e25-eacc-4b17-9196-021904dc235b",
  "preflightStatus": "ready_for_review",
  "productionEligible": false,
  "outputRoot": "tmp\\real012-paper-artifacts",
  "manifestPath": "tmp\\real012-paper-artifacts\\kqg-s010b-paper-artifacts.manifest.json",
  "manifestSha256": "584a6957d4418c937a9a6aa9dbc886b84a6775fd318d9cc99c7c683af9af5253",
  "variants": {
    "student": {
      "label": "学生版",
      "docxPath": "tmp\\real012-paper-artifacts\\kqg-s010b-student-paper.docx",
      "docxSha256": "47c8292a2d59d8f79f422b945e809edbec4c9446b415e2664e53048520a98866",
      "pdfPath": "tmp\\real012-paper-artifacts\\kqg-s010b-student-paper.pdf",
      "pdfSha256": "4959a847c86f4dad9e4a2312dcf156876672d9b56e1909ab698decc4296acaff"
    },
    "teacher": {
      "label": "教师版",
      "docxPath": "tmp\\real012-paper-artifacts\\kqg-s010b-teacher-paper.docx",
      "docxSha256": "d9627bc6e628a7d2b5b5b2cbc59ab0804beb68cb2b5d695f13d5da1315417be7",
      "pdfPath": "tmp\\real012-paper-artifacts\\kqg-s010b-teacher-paper.pdf",
      "pdfSha256": "5cf0dd637436ee357b15a090375c81bc54f1af9baa1f4ca4f0213c2d7c8999b0"
    },
    "answer": {
      "label": "答案版",
      "docxPath": "tmp\\real012-paper-artifacts\\kqg-s010b-answer-paper.docx",
      "docxSha256": "e11577a4eedf079a00a5b8cac161e35627e284b58d9b0715c0c1335ba3d25505",
      "pdfPath": "tmp\\real012-paper-artifacts\\kqg-s010b-answer-paper.pdf",
      "pdfSha256": "3f7ffe7de40a5545cc65dc9f05a85023d98089bec8633d2e569bbeadc94b7df3"
    }
  },
  "checks": {
    "student": {
      "docx": {
        "hasDocumentXml": true,
        "hasFormulaText": false,
        "hasFigureMedia": true,
        "hasTable": false,
        "hasSourceAuthorization": true,
        "hasKnowledgeVersionReference": true,
        "hasAnswer": false,
        "hasSolution": false,
        "studentHidesAnswer": true,
        "mediaCount": 3
      },
      "pdf": {
        "hasPdfHeader": true,
        "hasEof": true,
        "hasTaskMarker": true
      }
    },
    "teacher": {
      "docx": {
        "hasDocumentXml": true,
        "hasFormulaText": false,
        "hasFigureMedia": true,
        "hasTable": false,
        "hasSourceAuthorization": true,
        "hasKnowledgeVersionReference": true,
        "hasAnswer": true,
        "hasSolution": true,
        "studentHidesAnswer": true,
        "mediaCount": 3
      },
      "pdf": {
        "hasPdfHeader": true,
        "hasEof": true,
        "hasTaskMarker": true
      }
    },
    "answer": {
      "docx": {
        "hasDocumentXml": true,
        "hasFormulaText": false,
        "hasFigureMedia": true,
        "hasTable": true,
        "hasSourceAuthorization": true,
        "hasKnowledgeVersionReference": true,
        "hasAnswer": true,
        "hasSolution": true,
        "studentHidesAnswer": true,
        "mediaCount": 0
      },
      "pdf": {
        "hasPdfHeader": true,
        "hasEof": true,
        "hasTaskMarker": true
      }
    }
  },
  "requirements": {
    "requiresFormula": false,
    "requiresTable": false
  },
  "conclusion": "student teacher and answer Word/PDF artifacts were generated from a ready_for_review paper basket and verified by manifest hashes",
  "rollback": "delete tmp/s010b-paper-artifacts and revert the S010B smoke/gate/status changes; no database migration or active switch is involved"
}
