{
  "status": "pass",
  "taskId": "S010B",
  "checkedAt": "2026-06-15T00:16:13.092881+08:00",
  "paperBasketId": "cd340e14-aadd-46b9-91ea-4e873d0da393",
  "preflightStatus": "ready_for_review",
  "productionEligible": false,
  "outputRoot": "tmp\\s010b-paper-artifacts",
  "manifestPath": "tmp\\s010b-paper-artifacts\\kqg-s010b-paper-artifacts.manifest.json",
  "manifestSha256": "56b78c0c8e7061408719f85f638bdd6788a48e53ebb2db9747af17c43977d66b",
  "variants": {
    "student": {
      "label": "学生版",
      "docxPath": "tmp\\s010b-paper-artifacts\\kqg-s010b-student-paper.docx",
      "docxSha256": "7913e573b19a13b32b97010a56e4679f33804748c545481bb72b9914e3143670",
      "pdfPath": "tmp\\s010b-paper-artifacts\\kqg-s010b-student-paper.pdf",
      "pdfSha256": "712f11d9239405a0ce992017b313ecfff29d3b48bd0f5b8a535379ae66f0e5fb"
    },
    "teacher": {
      "label": "教师版",
      "docxPath": "tmp\\s010b-paper-artifacts\\kqg-s010b-teacher-paper.docx",
      "docxSha256": "8dd9fa71e89946482803f5b6c3187604b8d045642257f698c2e4ab32dda15a83",
      "pdfPath": "tmp\\s010b-paper-artifacts\\kqg-s010b-teacher-paper.pdf",
      "pdfSha256": "be8cc0a7f30965b041392515951ab862dab5804fcc0df577d35bbf247bd8d225"
    },
    "answer": {
      "label": "答案版",
      "docxPath": "tmp\\s010b-paper-artifacts\\kqg-s010b-answer-paper.docx",
      "docxSha256": "90df620407fcd8c0b000dc9cff7304a319ea7dee0a50b4135ed6cf943be2129c",
      "pdfPath": "tmp\\s010b-paper-artifacts\\kqg-s010b-answer-paper.pdf",
      "pdfSha256": "7d9158a54c103b022e17631e4f4e4d01c3cb57480a5fc59c6dd35eea0f39c078"
    }
  },
  "checks": {
    "student": {
      "docx": {
        "hasDocumentXml": true,
        "hasFormulaText": true,
        "hasFigureMedia": true,
        "hasTable": true,
        "hasSourceAuthorization": true,
        "hasKnowledgeVersionReference": true,
        "hasAnswer": false,
        "hasSolution": false,
        "studentHidesAnswer": true,
        "mediaCount": 1
      },
      "pdf": {
        "hasPdfHeader": true,
        "hasEof": true,
        "hasTaskMarker": true
      }
    },
    "teacher": {
      "docx": {
        "hasDocumentXml": true,
        "hasFormulaText": true,
        "hasFigureMedia": true,
        "hasTable": true,
        "hasSourceAuthorization": true,
        "hasKnowledgeVersionReference": true,
        "hasAnswer": true,
        "hasSolution": true,
        "studentHidesAnswer": true,
        "mediaCount": 1
      },
      "pdf": {
        "hasPdfHeader": true,
        "hasEof": true,
        "hasTaskMarker": true
      }
    },
    "answer": {
      "docx": {
        "hasDocumentXml": true,
        "hasFormulaText": false,
        "hasFigureMedia": true,
        "hasTable": true,
        "hasSourceAuthorization": true,
        "hasKnowledgeVersionReference": true,
        "hasAnswer": true,
        "hasSolution": true,
        "studentHidesAnswer": true,
        "mediaCount": 0
      },
      "pdf": {
        "hasPdfHeader": true,
        "hasEof": true,
        "hasTaskMarker": true
      }
    }
  },
  "requirements": {
    "requiresFormula": true,
    "requiresTable": true
  },
  "conclusion": "student teacher and answer Word/PDF artifacts were generated from a ready_for_review paper basket and verified by manifest hashes",
  "rollback": "delete tmp/s010b-paper-artifacts and revert the S010B smoke/gate/status changes; no database migration or active switch is involved",
  "requestedApiPort": 10606,
  "resolvedApiPort": 10606,
  "portFallbackApplied": false
}
