{
  "status": "pass",
  "taskId": "S009B",
  "checkedAt": "2026-06-23T23:50:34",
  "requestedApiPort": 7291,
  "resolvedApiPort": 7291,
  "portFallbackApplied": false,
  "blueprintReviewId": "b6c44a3e-2d1a-4d46-be2e-78e78ac3aaa5",
  "initialStatus": "pending_review",
  "finalStatus": "confirmed",
  "paperBasketId": "0cc68839-c40e-4e80-b053-8284982eb0af",
  "selectedQuestionCount": 8,
  "reviewRequiredBeforeQuestionSelection": true,
  "opaqueGenerationAllowed": false,
  "allowRealModelCalls": false,
  "productionEligible": false,
  "conclusion": "natural-language paper request creates a reviewable blueprint first; only explicit teacher confirmation creates a draft paper basket and selects questions",
  "rollback": "delete the created paper_blueprint_reviews row and related draft paper_baskets/paper_basket_items, or revert the S009B migration before release"
}
