{
  "status": "pass",
  "taskId": "S009A",
  "checkedAt": "2026-06-23T23:45:00",
  "requestedApiPort": 3692,
  "resolvedApiPort": 3692,
  "portFallbackApplied": false,
  "basketId": "dd25a890-e9b4-4022-b203-24123c667de8",
  "itemCount": 2,
  "questionNumbers": [
    1,
    2
  ],
  "subQuestionNumbers": [
    null,
    "2-1"
  ],
  "totalScore": 8,
  "knowledgeVersionStatus": "active",
  "knowledgeVersion": 1,
  "conclusion": "paper basket persists paper structure question numbers scores sub-question numbers and active knowledge version references"
}
