{
  "status": "pass",
  "taskId": "S009B",
  "checkedAt": "2026-05-30T10:31:15",
  "blueprintReviewId": "48e05459-c2f0-4d8a-a797-537adc44cf6e",
  "initialStatus": "pending_review",
  "finalStatus": "confirmed",
  "paperBasketId": "ef9e06ff-99c1-4b94-a772-854e801a5444",
  "selectedQuestionCount": 8,
  "reviewRequiredBeforeQuestionSelection": true,
  "opaqueGenerationAllowed": false,
  "allowRealModelCalls": false,
  "productionEligible": false,
  "conclusion": "natural-language paper request creates a reviewable blueprint first; only explicit teacher confirmation creates a draft paper basket and selects questions",
  "rollback": "delete the created paper_blueprint_reviews row and related draft paper_baskets/paper_basket_items, or revert the S009B migration before release"
}
