{
  "status": "pass",
  "taskId": "S009B",
  "checkedAt": "2026-06-21T00:56:44",
  "requestedApiPort": 13970,
  "resolvedApiPort": 13970,
  "portFallbackApplied": false,
  "blueprintReviewId": "7bc81f4c-1075-489d-bfa6-804e8a169096",
  "initialStatus": "pending_review",
  "finalStatus": "confirmed",
  "paperBasketId": "231b16ef-f325-41f6-9b38-e1488c002671",
  "selectedQuestionCount": 8,
  "reviewRequiredBeforeQuestionSelection": true,
  "opaqueGenerationAllowed": false,
  "allowRealModelCalls": false,
  "productionEligible": false,
  "conclusion": "natural-language paper request creates a reviewable blueprint first; only explicit teacher confirmation creates a draft paper basket and selects questions",
  "rollback": "delete the created paper_blueprint_reviews row and related draft paper_baskets/paper_basket_items, or revert the S009B migration before release"
}
