{
  "status": "pass",
  "taskId": "NS306",
  "checkedAt": "2026-06-23T21:17:05",
  "mode": "j003_scanned_ocr_adapter_contract_wrapper",
  "productionEligible": false,
  "dependency": {
    "task": "J003",
    "report": "docs/evidence/j003-scanned-ocr-adapter-report.json",
    "scannedPdfAdapter": "rapidocr_scanned_pdf_adapter",
    "scannedImageAdapter": "rapidocr_image_adapter",
    "adapterVersion": "0.1"
  },
  "ocr": {
    "engineAvailable": true,
    "scannedPdfPageCount": 1,
    "scannedPdfBlockCount": 2,
    "scannedImageBlockCount": 2,
    "realOcrTextRecognized": true,
    "reviewStatus": "pending_review",
    "takeoverRequired": true,
    "invalidTakeoverBlockCount": 1
  },
  "acceptance": {
    "scannedPdfOcrRuns": true,
    "scannedImageOcrRuns": true,
    "confidenceAndSourceRegionsCovered": true,
    "failureFallsBackToPendingReviewTakeover": true,
    "syntheticGoldenOnly": true
  },
  "boundary": "NS306 proves RapidOCR scanned PDF/image adapters produce pending_review OCR blocks and invalid images fail closed to manual takeover. It does not claim production OCR accuracy for real school materials.",
  "next": "NS307 can continue SourceRegion screenshot path invariants after PDF/OCR adapter evidence.",
  "rollback": "git restore tasks/non-site-implementation-plan.csv tools/run-gates.ps1; git clean -f -- tools/run-ns306-scan-ocr-adapter.ps1 docs/evidence/20260530-ns306-scan-ocr-adapter-report.json"
}
