{
  "status": "pass",
  "taskId": "S007C",
  "checkedAt": "2026-06-07T02:52:14",
  "runId": "ns504-c3e7e902c42f47058f9c8f55155d3e08-c",
  "aiJobId": "7d9cc1d8-0646-43c7-af6e-6e96924e2c42",
  "confirm": {
    "questionItemId": "6ca26220-cd5e-431b-a1ba-d7a63a317400",
    "knowledgeMappingId": "910a7f70-9070-4d84-aba4-d6d62d22c483",
    "status": "confirmed"
  },
  "undo": {
    "removedQuestionItemId": "6ca26220-cd5e-431b-a1ba-d7a63a317400",
    "removedKnowledgeMappingCount": 1,
    "status": "undone"
  },
  "questionCount": {
    "before": 6815,
    "afterConfirm": 6816,
    "afterUndo": 6815
  },
  "conclusion": "teacher confirmation writes QuestionItem and KnowledgeMapping only after review, and undo restores previous state"
}
