{
  "status": "pass",
  "taskId": "S006B",
  "checkedAt": "2026-05-09T12:44:20",
  "sourceDocumentId": "c408f13a-c8c6-4619-aa10-7921a04536c2",
  "actions": {
    "merge": {
      "touched": 3,
      "createdCandidates": 0
    },
    "split": {
      "touched": 1,
      "createdCandidates": 2
    },
    "associate": {
      "touched": 1
    },
    "save_question": {
      "touched": 1,
      "createdQuestionId": "789742f6-53e2-4f3c-9da3-2f1dd1415b8e"
    }
  },
  "conclusion": "manual takeover workbench API supports merge split associate and save question chain"
}
